straps-0.1.4.dist-info/COPYING
straps-0.1.4.dist-info/top_level.txt
straps-0.1.4.dist-info/RECORD
straps-0.1.4.dist-info/METADATA
straps-0.1.4.dist-info/WHEEL
straps/sh_pdt.py
straps/rpe_sec.py
straps/simple_circuits.py
straps/secfig.py
straps/pdt_matrix_plot.py
straps/utils.py
straps/paper_plots.py
straps/circuit_model.py
straps/eval_circs.py
straps/__init__.py
straps/pdt_sampling.py
straps/_straps_ext.cpython-312-x86_64-linux-gnu.so
straps/probe_distr.py
