Metadata-Version: 2.1
Name: straps
Version: 0.1.4
Summary: Statistical Testing of RAndom Probing Security
Home-page: https://github.com/cassiersg/straps
Author: Gaëtan Cassiers
Author-email: gaetan.cassiers@uclouvain.be
Project-URL: Bug Tracker, https://github.com/cassiersg/straps/issues
Classifier: Programming Language :: Python :: 3
Requires-Python: >=3.10
License-File: COPYING
Requires-Dist: joblib~=1.4.2
Requires-Dist: matplotlib~=3.8.4
Requires-Dist: numpy~=1.26.4
Requires-Dist: tqdm~=4.66.1
